README.md
setup.py
py2nsis.egg-info/PKG-INFO
py2nsis.egg-info/SOURCES.txt
py2nsis.egg-info/dependency_links.txt
py2nsis.egg-info/entry_points.txt
py2nsis.egg-info/top_level.txt
py2nsis/bin/7z/7z.dll
py2nsis/bin/7z/7z.exe
py2nsis/bin/NSIS/COPYING
py2nsis/bin/NSIS/NSIS.chm
py2nsis/bin/NSIS/NSIS.exe
py2nsis/bin/NSIS/makensis.exe
py2nsis/bin/NSIS/makensisw.exe
py2nsis/bin/NSIS/nsisconf.nsh
py2nsis/bin/NSIS/Bin/GenPat.exe
py2nsis/bin/NSIS/Bin/LibraryLocal.exe
py2nsis/bin/NSIS/Bin/MakeLangId.exe
py2nsis/bin/NSIS/Bin/RegTool.bin
py2nsis/bin/NSIS/Bin/zip2exe.exe
py2nsis/bin/NSIS/Contrib/Graphics/Checks/big.bmp
py2nsis/bin/NSIS/Contrib/Graphics/Checks/classic-cross.bmp
py2nsis/bin/NSIS/Contrib/Graphics/Checks/classic.bmp
py2nsis/bin/NSIS/Contrib/Graphics/Checks/colorful.bmp
py2nsis/bin/NSIS/Contrib/Graphics/Checks/grey-cross.bmp
py2nsis/bin/NSIS/Contrib/Graphics/Checks/grey.bmp
py2nsis/bin/NSIS/Contrib/Graphics/Checks/modern.bmp
py2nsis/bin/NSIS/Contrib/Graphics/Checks/red-round.bmp
py2nsis/bin/NSIS/Contrib/Graphics/Checks/red.bmp
py2nsis/bin/NSIS/Contrib/Graphics/Checks/simple-round.bmp
py2nsis/bin/NSIS/Contrib/Graphics/Checks/simple-round2.bmp
py2nsis/bin/NSIS/Contrib/Graphics/Checks/simple.bmp
py2nsis/bin/NSIS/Contrib/Graphics/Header/nsis-r.bmp
py2nsis/bin/NSIS/Contrib/Graphics/Header/nsis.bmp
py2nsis/bin/NSIS/Contrib/Graphics/Header/orange-nsis.bmp
py2nsis/bin/NSIS/Contrib/Graphics/Header/orange-r-nsis.bmp
py2nsis/bin/NSIS/Contrib/Graphics/Header/orange-r.bmp
py2nsis/bin/NSIS/Contrib/Graphics/Header/orange-uninstall-nsis.bmp
py2nsis/bin/NSIS/Contrib/Graphics/Header/orange-uninstall-r-nsis.bmp
py2nsis/bin/NSIS/Contrib/Graphics/Header/orange-uninstall-r.bmp
py2nsis/bin/NSIS/Contrib/Graphics/Header/orange-uninstall.bmp
py2nsis/bin/NSIS/Contrib/Graphics/Header/orange.bmp
py2nsis/bin/NSIS/Contrib/Graphics/Header/win.bmp
py2nsis/bin/NSIS/Contrib/Graphics/Icons/arrow-install.ico
py2nsis/bin/NSIS/Contrib/Graphics/Icons/arrow-uninstall.ico
py2nsis/bin/NSIS/Contrib/Graphics/Icons/arrow2-install.ico
py2nsis/bin/NSIS/Contrib/Graphics/Icons/arrow2-uninstall.ico
py2nsis/bin/NSIS/Contrib/Graphics/Icons/box-install.ico
